prompt_storage/__init__.py
prompt_storage/google_docs_cache_manager.py
prompt_storage/google_docs_processor.py
prompt_storage/logger.py
prompt_storage/prompt_storage.py
prompt_storage/template_processor.py
prompt_storage-0.1.7.post19.dist-info/METADATA
prompt_storage-0.1.7.post19.dist-info/WHEEL
prompt_storage-0.1.7.post19.dist-info/top_level.txt
prompt_storage-0.1.7.post19.dist-info/RECORD
