Metadata-Version: 2.4
Name: prompt-storage
Version: 0.1.7.post19
Summary: Library for managing and caching Google Docs prompts with templating support.
Author-email: Albert Toma <cornil@mail.ru>
License: MIT
Project-URL: Homepage, https://github.com/Cornil79/prompt-storage
Project-URL: Repository, https://github.com/Cornil79/prompt-storage
Project-URL: Documentation, https://Cornil79.github.io/prompt-storage
Classifier: License :: OSI Approved :: MIT License
Classifier: Programming Language :: Python :: 3
Classifier: Operating System :: OS Independent
Requires-Python: >=3.8
Requires-Dist: google-api-python-client>=2.0.0
Requires-Dist: google-auth>=2.0.0
Requires-Dist: google-auth-oauthlib>=1.0.0
Requires-Dist: python-docx>=1.0.0
Requires-Dist: jinja2>=3.0.0
Requires-Dist: mako>=1.0.0
Provides-Extra: api
Requires-Dist: fastapi>=0.100.0; extra == "api"
Provides-Extra: full
Requires-Dist: fastapi>=0.100.0; extra == "full"
